<?xml version="1.0" encoding="UTF-8"?>
<!DOCTYPE mapper PUBLIC "-//mybatis.org//DTD Mapper 3.0//EN" "http://mybatis.org/dtd/mybatis-3-mapper.dtd">
<mapper namespace="com.zuoer.sofa.blog.dal.dao.TagMapper">
  <resultMap id="BaseResultMap" type="com.zuoer.sofa.blog.dal.dateobject.TagDO">
    <result column="ID" jdbcType="DECIMAL" property="id" />
    <result column="NAME" jdbcType="VARCHAR" property="name" />
    <result column="GMT_CREATE" jdbcType="TIMESTAMP" property="gmtCreate" />
    <result column="GMT_MODIFIED" jdbcType="TIMESTAMP" property="gmtModified" />
    <!--
      WARNING - @mbg.generated
      This element is automatically generated by MyBatis Generator, do not modify.
    -->
  </resultMap>
  <select id="selectById" resultMap="BaseResultMap">
    <!--
      WARNING - @mbg.generated
      This element is automatically generated by MyBatis Generator, do not modify.
    -->
    
			select id,name,  gmt_create, gmt_modified  from tag  where id=#{id} 
  </select>
  <insert id="insert">
    <!--
      WARNING - @mbg.generated
      This element is automatically generated by MyBatis Generator, do not modify.
    -->
    
			insert into tag(  id,name,  gmt_create, gmt_modified) values (#{id},#{name})
  </insert>
  <select id="selectByName" resultMap="BaseResultMap">
    <!--
      WARNING - @mbg.generated
      This element is automatically generated by MyBatis Generator, do not modify.
    -->
    
			select id,name,  gmt_create, gmt_modified  from tag  where name=#{name} 
  </select>
  <select id="selectAll" resultMap="BaseResultMap">
    <!--
      WARNING - @mbg.generated
      This element is automatically generated by MyBatis Generator, do not modify.
    -->
    
			select id,name,  gmt_create, gmt_modified  from tag
		
  </select>
</mapper>